{
    "positions": [
        {
            "analyses": [
                {
                    "is_omitted": false,
                    "record_id": "29746-01",
                    "uuid": "dff362c0-5463-46d4-9681-26a2f0d1adaa"
                },
                {
                    "is_omitted": false,
                    "record_id": "29746-02",
                    "uuid": "a41f8607-be37-483b-9533-36ccb1884c97"
                },
                {
                    "is_omitted": false,
                    "record_id": "29746-03",
                    "uuid": "fe771bc9-5d48-4069-bd00-eef1926cfe3d"
                },
                {
                    "is_omitted": false,
                    "record_id": "29746-04",
                    "uuid": "bd0d92c9-4af5-4879-a16e-af5222eb9a21"
                },
                {
                    "is_omitted": false,
                    "record_id": "29746-05",
                    "uuid": "fe5fa4f1-fe32-4007-87a9-a83ea8ec2fab"
                },
                {
                    "is_omitted": false,
                    "record_id": "29746-06",
                    "uuid": "eff75910-5ced-46b4-aefd-e36f552a94b8"
                },
                {
                    "is_omitted": false,
                    "record_id": "29746-07",
                    "uuid": "a79bdb09-0fd3-4cb6-aee6-f1344aacb79c"
                }
            ],
            "decay_constants": {
                "lambda_k_total": 5.463e-10,
                "lambda_k_total_error": 9.998499887483122e-12
            },
            "identifier": "29746",
            "j": 0.005829884895123628,
            "j_err": 5.8187519760809666e-06,
            "mean_j": 0.005829496144614359,
            "mean_j_err": 2.567946433690124e-05,
            "mean_j_mswd": 13.008599563051064,
            "options": {
                "interpolation_style": "Weighted Mean",
                "model_kind": "Bracketing",
                "monitor_age": 28.201,
                "monitor_material": "FC-2",
                "monitor_name": "FC-2",
                "monitor_reference": "FC Min",
                "monte_carlo_ntrials": 10,
                "predicted_j_error_type": "SE but if MSWD>1 use SE * sqrt(MSWD)",
                "use_monte_carlo": false,
                "use_weighted_fit": false
            },
            "position": 1,
            "position_jerr": 0.0
        },
        {
            "analyses": [],
            "decay_constants": {
                "lambda_k_total": 5.463e-10,
                "lambda_k_total_error": 9.998499887483122e-12
            },
            "identifier": "71412",
            "j": 0.005829884895123628,
            "j_err": 5.8187519760809666e-06,
            "mean_j": 0.0,
            "mean_j_err": 0.0,
            "mean_j_mswd": 0.0,
            "options": {
                "interpolation_style": "Weighted Mean",
                "model_kind": "Bracketing",
                "monitor_age": 28.201,
                "monitor_material": "FC-2",
                "monitor_name": "FC-2",
                "monitor_reference": "FC Min",
                "monte_carlo_ntrials": 10,
                "predicted_j_error_type": "SE but if MSWD>1 use SE * sqrt(MSWD)",
                "use_monte_carlo": false,
                "use_weighted_fit": false
            },
            "position": 2,
            "position_jerr": 0.0
        },
        {
            "analyses": [],
            "decay_constants": {
                "lambda_k_total": 5.463e-10,
                "lambda_k_total_error": 9.998499887483122e-12
            },
            "identifier": "71413",
            "j": 0.005829884895123628,
            "j_err": 5.8187519760809666e-06,
            "mean_j": 0.0,
            "mean_j_err": 0.0,
            "mean_j_mswd": 0.0,
            "options": {
                "interpolation_style": "Weighted Mean",
                "model_kind": "Bracketing",
                "monitor_age": 28.201,
                "monitor_material": "FC-2",
                "monitor_name": "FC-2",
                "monitor_reference": "FC Min",
                "monte_carlo_ntrials": 10,
                "predicted_j_error_type": "SE but if MSWD>1 use SE * sqrt(MSWD)",
                "use_monte_carlo": false,
                "use_weighted_fit": false
            },
            "position": 3,
            "position_jerr": 0.0
        },
        {
            "analyses": [
                {
                    "is_omitted": false,
                    "record_id": "29747-01",
                    "uuid": "7a7fdd1d-9633-4099-94c2-17e8f52da9f7"
                },
                {
                    "is_omitted": false,
                    "record_id": "29747-02",
                    "uuid": "031055f0-1759-4115-a036-16134d4fb2aa"
                },
                {
                    "is_omitted": false,
                    "record_id": "29747-03",
                    "uuid": "c16fce2e-7ae8-42b8-9700-2da61a58da96"
                },
                {
                    "is_omitted": false,
                    "record_id": "29747-04",
                    "uuid": "b721b2b5-9378-426f-ba56-022c27e8bfe2"
                },
                {
                    "is_omitted": false,
                    "record_id": "29747-05",
                    "uuid": "0c866980-a7ee-42ff-9bfb-e77024fccdf5"
                },
                {
                    "is_omitted": false,
                    "record_id": "29747-06",
                    "uuid": "6a01bea1-a2e2-4ad1-84fc-683c79e9214c"
                },
                {
                    "is_omitted": true,
                    "record_id": "29747-07",
                    "uuid": "89f6f65e-d1b9-4c5b-a21a-8a7829547ccb"
                },
                {
                    "is_omitted": true,
                    "record_id": "29747-08",
                    "uuid": "16490e72-9419-4118-81dc-18b6968c9390"
                }
            ],
            "decay_constants": {
                "lambda_k_total": 5.463e-10,
                "lambda_k_total_error": 9.998499887483122e-12
            },
            "identifier": "29747",
            "j": 0.005829884895123628,
            "j_err": 5.8187519760809666e-06,
            "mean_j": 0.0058299059353244045,
            "mean_j_err": 5.974140260013943e-06,
            "mean_j_mswd": 2.935898803092402,
            "options": {
                "interpolation_style": "Weighted Mean",
                "model_kind": "Bracketing",
                "monitor_age": 28.201,
                "monitor_material": "FC-2",
                "monitor_name": "FC-2",
                "monitor_reference": "FC Min",
                "monte_carlo_ntrials": 10,
                "predicted_j_error_type": "SE but if MSWD>1 use SE * sqrt(MSWD)",
                "use_monte_carlo": false,
                "use_weighted_fit": false
            },
            "position": 4,
            "position_jerr": 0.0
        },
        {
            "analyses": [],
            "decay_constants": {
                "lambda_k_total": 5.463e-10,
                "lambda_k_total_error": 9.998499887483122e-12
            },
            "identifier": "71414",
            "j": 0.005828826621108572,
            "j_err": 5.592298775210807e-06,
            "mean_j": 0.0,
            "mean_j_err": 0.0,
            "mean_j_mswd": 0.0,
            "options": {
                "interpolation_style": "Weighted Mean",
                "model_kind": "Bracketing",
                "monitor_age": 28.201,
                "monitor_material": "FC-2",
                "monitor_name": "FC-2",
                "monitor_reference": "FC Min",
                "monte_carlo_ntrials": 10,
                "predicted_j_error_type": "SE but if MSWD>1 use SE * sqrt(MSWD)",
                "use_monte_carlo": false,
                "use_weighted_fit": false
            },
            "position": 5,
            "position_jerr": 0.0
        },
        {
            "analyses": [],
            "decay_constants": {
                "lambda_k_total": 5.463e-10,
                "lambda_k_total_error": 9.998499887483122e-12
            },
            "identifier": "71415",
            "j": 0.005828826621108572,
            "j_err": 5.592298775210807e-06,
            "mean_j": 0.0,
            "mean_j_err": 0.0,
            "mean_j_mswd": 0.0,
            "options": {
                "interpolation_style": "Weighted Mean",
                "model_kind": "Bracketing",
                "monitor_age": 28.201,
                "monitor_material": "FC-2",
                "monitor_name": "FC-2",
                "monitor_reference": "FC Min",
                "monte_carlo_ntrials": 10,
                "predicted_j_error_type": "SE but if MSWD>1 use SE * sqrt(MSWD)",
                "use_monte_carlo": false,
                "use_weighted_fit": false
            },
            "position": 6,
            "position_jerr": 0.0
        },
        {
            "analyses": [
                {
                    "is_omitted": false,
                    "record_id": "29748-01",
                    "uuid": "e99afd9e-c856-44ef-a8a8-abe283ea6d4e"
                },
                {
                    "is_omitted": false,
                    "record_id": "29748-02",
                    "uuid": "f971173a-b773-4a93-8179-4deba49a1d7d"
                },
                {
                    "is_omitted": false,
                    "record_id": "29748-03",
                    "uuid": "13990bcd-de70-4d5f-9f79-78ae096144ac"
                },
                {
                    "is_omitted": false,
                    "record_id": "29748-04",
                    "uuid": "bdeda157-0d13-4c42-9245-ab16f000f69d"
                },
                {
                    "is_omitted": false,
                    "record_id": "29748-05",
                    "uuid": "76445b6d-c2d0-426a-ae0c-7c1e5abc2827"
                },
                {
                    "is_omitted": false,
                    "record_id": "29748-06",
                    "uuid": "5a08f9e3-0993-4baa-b3d6-2dbff18436b1"
                },
                {
                    "is_omitted": false,
                    "record_id": "29748-07",
                    "uuid": "f0cd156f-3ef1-461c-b965-8c2d6cdb00e1"
                },
                {
                    "is_omitted": false,
                    "record_id": "29748-08",
                    "uuid": "6e210981-7a3e-4824-81c3-3af581e38420"
                }
            ],
            "decay_constants": {
                "lambda_k_total": 5.463e-10,
                "lambda_k_total_error": 9.998499887483122e-12
            },
            "identifier": "29748",
            "j": 0.005828826621108572,
            "j_err": 5.592298775210807e-06,
            "mean_j": 0.005821183938114184,
            "mean_j_err": 1.589733730768878e-05,
            "mean_j_mswd": 10.165332225946253,
            "options": {
                "interpolation_style": "Weighted Mean",
                "model_kind": "Bracketing",
                "monitor_age": 28.201,
                "monitor_material": "FC-2",
                "monitor_name": "FC-2",
                "monitor_reference": "FC Min",
                "monte_carlo_ntrials": 10,
                "predicted_j_error_type": "SE but if MSWD>1 use SE * sqrt(MSWD)",
                "use_monte_carlo": false,
                "use_weighted_fit": false
            },
            "position": 7,
            "position_jerr": 0.0
        },
        {
            "analyses": [],
            "decay_constants": {
                "lambda_k_total": 5.463e-10,
                "lambda_k_total_error": 9.998499887483122e-12
            },
            "identifier": "71416",
            "j": 0.005823089249503605,
            "j_err": 1.5043082577588822e-05,
            "mean_j": 0.0,
            "mean_j_err": 0.0,
            "mean_j_mswd": 0.0,
            "options": {
                "interpolation_style": "Weighted Mean",
                "model_kind": "Bracketing",
                "monitor_age": 28.201,
                "monitor_material": "FC-2",
                "monitor_name": "FC-2",
                "monitor_reference": "FC Min",
                "monte_carlo_ntrials": 10,
                "predicted_j_error_type": "SE but if MSWD>1 use SE * sqrt(MSWD)",
                "use_monte_carlo": false,
                "use_weighted_fit": false
            },
            "position": 8,
            "position_jerr": 0.0
        },
        {
            "analyses": [],
            "decay_constants": {
                "lambda_k_total": 5.463e-10,
                "lambda_k_total_error": 9.998499887483122e-12
            },
            "identifier": "71417",
            "j": 0.005823089249503605,
            "j_err": 1.5043082577588822e-05,
            "mean_j": 0.0,
            "mean_j_err": 0.0,
            "mean_j_mswd": 0.0,
            "options": {
                "interpolation_style": "Weighted Mean",
                "model_kind": "Bracketing",
                "monitor_age": 28.201,
                "monitor_material": "FC-2",
                "monitor_name": "FC-2",
                "monitor_reference": "FC Min",
                "monte_carlo_ntrials": 10,
                "predicted_j_error_type": "SE but if MSWD>1 use SE * sqrt(MSWD)",
                "use_monte_carlo": false,
                "use_weighted_fit": false
            },
            "position": 9,
            "position_jerr": 0.0
        },
        {
            "analyses": [
                {
                    "is_omitted": false,
                    "record_id": "29749-01",
                    "uuid": "d96797e2-de66-4949-a8ed-442ee899604f"
                },
                {
                    "is_omitted": false,
                    "record_id": "29749-02",
                    "uuid": "578ec80e-0810-434d-a098-427d6dc869ca"
                },
                {
                    "is_omitted": false,
                    "record_id": "29749-03",
                    "uuid": "1ecc47de-cb2f-4c75-bebc-c087c50717c2"
                },
                {
                    "is_omitted": true,
                    "record_id": "29749-04",
                    "uuid": "9634e2b2-c9cc-4e44-8d1e-dc3b9e6dc359"
                },
                {
                    "is_omitted": false,
                    "record_id": "29749-05",
                    "uuid": "21ffe2c4-866d-4369-b5a9-0a298c23d3a1"
                },
                {
                    "is_omitted": false,
                    "record_id": "29749-06",
                    "uuid": "ca556eee-86e0-477a-87cd-e096b90fe75c"
                },
                {
                    "is_omitted": true,
                    "record_id": "29749-07",
                    "uuid": "f5513a8d-42ca-4584-8049-98208a097f6d"
                },
                {
                    "is_omitted": false,
                    "record_id": "29749-08",
                    "uuid": "908d64c1-01d7-412d-8ace-7c70627a299f"
                }
            ],
            "decay_constants": {
                "lambda_k_total": 5.463e-10,
                "lambda_k_total_error": 9.998499887483122e-12
            },
            "identifier": "29749",
            "j": 0.005823089249503605,
            "j_err": 1.5043082577588822e-05,
            "mean_j": 0.0058394019569393005,
            "mean_j_err": 4.651622162194052e-05,
            "mean_j_mswd": 26.5221249714873,
            "options": {
                "interpolation_style": "Weighted Mean",
                "model_kind": "Bracketing",
                "monitor_age": 28.201,
                "monitor_material": "FC-2",
                "monitor_name": "FC-2",
                "monitor_reference": "FC Min",
                "monte_carlo_ntrials": 10,
                "predicted_j_error_type": "SE but if MSWD>1 use SE * sqrt(MSWD)",
                "use_monte_carlo": false,
                "use_weighted_fit": false
            },
            "position": 10,
            "position_jerr": 0.0
        },
        {
            "analyses": [],
            "decay_constants": {
                "lambda_k_total": 5.463e-10,
                "lambda_k_total_error": 9.998499887483122e-12
            },
            "identifier": "71418",
            "j": 0.005797017953380202,
            "j_err": 2.2527694864939853e-06,
            "mean_j": 0.0,
            "mean_j_err": 0.0,
            "mean_j_mswd": 0.0,
            "options": {
                "interpolation_style": "Weighted Mean",
                "model_kind": "Bracketing",
                "monitor_age": 28.201,
                "monitor_material": "FC-2",
                "monitor_name": "FC-2",
                "monitor_reference": "FC Min",
                "monte_carlo_ntrials": 10,
                "predicted_j_error_type": "SE but if MSWD>1 use SE * sqrt(MSWD)",
                "use_monte_carlo": false,
                "use_weighted_fit": false
            },
            "position": 11,
            "position_jerr": 0.0
        },
        {
            "analyses": [],
            "decay_constants": {
                "lambda_k_total": 5.463e-10,
                "lambda_k_total_error": 9.998499887483122e-12
            },
            "identifier": "71419",
            "j": 0.005797017953380202,
            "j_err": 2.2527694864939853e-06,
            "mean_j": 0.0,
            "mean_j_err": 0.0,
            "mean_j_mswd": 0.0,
            "options": {
                "interpolation_style": "Weighted Mean",
                "model_kind": "Bracketing",
                "monitor_age": 28.201,
                "monitor_material": "FC-2",
                "monitor_name": "FC-2",
                "monitor_reference": "FC Min",
                "monte_carlo_ntrials": 10,
                "predicted_j_error_type": "SE but if MSWD>1 use SE * sqrt(MSWD)",
                "use_monte_carlo": false,
                "use_weighted_fit": false
            },
            "position": 12,
            "position_jerr": 0.0
        },
        {
            "analyses": [
                {
                    "is_omitted": false,
                    "record_id": "29750-01",
                    "uuid": "661b8af5-da8a-44d9-bc59-626387e53b9d"
                },
                {
                    "is_omitted": true,
                    "record_id": "29750-02",
                    "uuid": "7e844849-803b-44c7-8637-68001dae0ba1"
                },
                {
                    "is_omitted": false,
                    "record_id": "29750-03",
                    "uuid": "94199070-1c76-4812-adf7-d929efbedac3"
                },
                {
                    "is_omitted": false,
                    "record_id": "29750-04",
                    "uuid": "c6b7c019-97eb-4412-b76e-44b821893da0"
                },
                {
                    "is_omitted": false,
                    "record_id": "29750-05",
                    "uuid": "9e6c5242-f0fc-4e46-b456-e722042131d2"
                },
                {
                    "is_omitted": false,
                    "record_id": "29750-06",
                    "uuid": "1e94ebc5-fdf2-43c4-bf87-ad0444f6a675"
                },
                {
                    "is_omitted": false,
                    "record_id": "29750-07",
                    "uuid": "a4628b44-4067-41ef-bb15-ddf21d67085c"
                },
                {
                    "is_omitted": true,
                    "record_id": "29750-08",
                    "uuid": "a24b9e79-82b5-4f69-a74e-ee230c1eea2a"
                }
            ],
            "decay_constants": {
                "lambda_k_total": 5.463e-10,
                "lambda_k_total_error": 9.998499887483122e-12
            },
            "identifier": "29750",
            "j": 0.005797017953380202,
            "j_err": 2.2527694864939853e-06,
            "mean_j": 0.005796918310462862,
            "mean_j_err": 2.2554160126418232e-06,
            "mean_j_mswd": 1.6981920518536626,
            "options": {
                "interpolation_style": "Weighted Mean",
                "model_kind": "Bracketing",
                "monitor_age": 28.201,
                "monitor_material": "FC-2",
                "monitor_name": "FC-2",
                "monitor_reference": "FC Min",
                "monte_carlo_ntrials": 10,
                "predicted_j_error_type": "SE but if MSWD>1 use SE * sqrt(MSWD)",
                "use_monte_carlo": false,
                "use_weighted_fit": false
            },
            "position": 13,
            "position_jerr": 0.0
        },
        {
            "analyses": [],
            "decay_constants": {
                "lambda_k_total": 5.463e-10,
                "lambda_k_total_error": 9.998499887483122e-12
            },
            "identifier": "71420",
            "j": 0.005796241942306286,
            "j_err": 2.214238987675932e-06,
            "mean_j": 0.0,
            "mean_j_err": 0.0,
            "mean_j_mswd": 0.0,
            "options": {
                "interpolation_style": "Weighted Mean",
                "model_kind": "Bracketing",
                "monitor_age": 28.201,
                "monitor_material": "FC-2",
                "monitor_name": "FC-2",
                "monitor_reference": "FC Min",
                "monte_carlo_ntrials": 10,
                "predicted_j_error_type": "SE but if MSWD>1 use SE * sqrt(MSWD)",
                "use_monte_carlo": false,
                "use_weighted_fit": false
            },
            "position": 14,
            "position_jerr": 0.0
        },
        {
            "analyses": [],
            "decay_constants": {
                "lambda_k_total": 5.463e-10,
                "lambda_k_total_error": 9.998499887483122e-12
            },
            "identifier": "71421",
            "j": 0.005796241942306286,
            "j_err": 2.214238987675932e-06,
            "mean_j": 0.0,
            "mean_j_err": 0.0,
            "mean_j_mswd": 0.0,
            "options": {
                "interpolation_style": "Weighted Mean",
                "model_kind": "Bracketing",
                "monitor_age": 28.201,
                "monitor_material": "FC-2",
                "monitor_name": "FC-2",
                "monitor_reference": "FC Min",
                "monte_carlo_ntrials": 10,
                "predicted_j_error_type": "SE but if MSWD>1 use SE * sqrt(MSWD)",
                "use_monte_carlo": false,
                "use_weighted_fit": false
            },
            "position": 15,
            "position_jerr": 0.0
        },
        {
            "analyses": [
                {
                    "is_omitted": false,
                    "record_id": "29751-01",
                    "uuid": "63207df3-cd9d-4685-bfc8-6180061fb8f7"
                },
                {
                    "is_omitted": false,
                    "record_id": "29751-02",
                    "uuid": "383b20b7-bf1a-4ca2-91cc-9a73596f5ad5"
                },
                {
                    "is_omitted": false,
                    "record_id": "29751-03",
                    "uuid": "a35d01b7-e2d6-4554-9ebb-def705b61adb"
                },
                {
                    "is_omitted": false,
                    "record_id": "29751-04",
                    "uuid": "ec2b3179-c8ed-4b6b-8530-8b3853c2cdfd"
                },
                {
                    "is_omitted": false,
                    "record_id": "29751-05",
                    "uuid": "74c28b9b-0b2c-4571-a7db-933b1f894368"
                },
                {
                    "is_omitted": false,
                    "record_id": "29751-06",
                    "uuid": "650a23e8-7793-4e82-a810-6c0114cb92e1"
                },
                {
                    "is_omitted": false,
                    "record_id": "29751-07",
                    "uuid": "fe53da8f-157c-4d59-8bc1-ae6c59fa8f81"
                },
                {
                    "is_omitted": false,
                    "record_id": "29751-08",
                    "uuid": "25a66360-f46a-4dbe-8cd5-6567c4a0ed77"
                }
            ],
            "decay_constants": {
                "lambda_k_total": 5.463e-10,
                "lambda_k_total_error": 9.998499887483122e-12
            },
            "identifier": "29751",
            "j": 0.005796241942306286,
            "j_err": 2.214238987675932e-06,
            "mean_j": 0.005778224083825613,
            "mean_j_err": 1.1640902956158793e-05,
            "mean_j_mswd": 8.315207928237282,
            "options": {
                "interpolation_style": "Weighted Mean",
                "model_kind": "Bracketing",
                "monitor_age": 28.201,
                "monitor_material": "FC-2",
                "monitor_name": "FC-2",
                "monitor_reference": "FC Min",
                "monte_carlo_ntrials": 10,
                "predicted_j_error_type": "SE but if MSWD>1 use SE * sqrt(MSWD)",
                "use_monte_carlo": false,
                "use_weighted_fit": false
            },
            "position": 16,
            "position_jerr": 0.0
        },
        {
            "analyses": [],
            "decay_constants": {
                "lambda_k_total": 5.463e-10,
                "lambda_k_total_error": 9.998499887483122e-12
            },
            "identifier": "71422",
            "j": 0.005772869064169085,
            "j_err": 3.2022500914947364e-06,
            "mean_j": 0.0,
            "mean_j_err": 0.0,
            "mean_j_mswd": 0.0,
            "options": {
                "interpolation_style": "Weighted Mean",
                "model_kind": "Bracketing",
                "monitor_age": 28.201,
                "monitor_material": "FC-2",
                "monitor_name": "FC-2",
                "monitor_reference": "FC Min",
                "monte_carlo_ntrials": 10,
                "predicted_j_error_type": "SE but if MSWD>1 use SE * sqrt(MSWD)",
                "use_monte_carlo": false,
                "use_weighted_fit": false
            },
            "position": 17,
            "position_jerr": 0.0
        },
        {
            "analyses": [],
            "decay_constants": {
                "lambda_k_total": 5.463e-10,
                "lambda_k_total_error": 9.998499887483122e-12
            },
            "identifier": "71423",
            "j": 0.005772869064169085,
            "j_err": 3.2022500914947364e-06,
            "mean_j": 0.0,
            "mean_j_err": 0.0,
            "mean_j_mswd": 0.0,
            "options": {
                "interpolation_style": "Weighted Mean",
                "model_kind": "Bracketing",
                "monitor_age": 28.201,
                "monitor_material": "FC-2",
                "monitor_name": "FC-2",
                "monitor_reference": "FC Min",
                "monte_carlo_ntrials": 10,
                "predicted_j_error_type": "SE but if MSWD>1 use SE * sqrt(MSWD)",
                "use_monte_carlo": false,
                "use_weighted_fit": false
            },
            "position": 18,
            "position_jerr": 0.0
        },
        {
            "analyses": [
                {
                    "is_omitted": true,
                    "record_id": "29752-01",
                    "uuid": "f793e27d-3827-4e64-9b2e-ea768463e5e3"
                },
                {
                    "is_omitted": false,
                    "record_id": "29752-02",
                    "uuid": "037f5bda-5870-480d-a2ca-b71e6677605d"
                },
                {
                    "is_omitted": false,
                    "record_id": "29752-03",
                    "uuid": "4b9393e5-0a8b-4c4f-a648-29b241405033"
                },
                {
                    "is_omitted": false,
                    "record_id": "29752-04",
                    "uuid": "fdad894c-3b01-4f3a-a99c-0977dc5e21e6"
                },
                {
                    "is_omitted": false,
                    "record_id": "29752-05",
                    "uuid": "3057af41-0285-4ced-9aa2-166d85a11d18"
                },
                {
                    "is_omitted": false,
                    "record_id": "29752-06",
                    "uuid": "dadb66f2-19f5-4f5c-af37-1388e5c13430"
                },
                {
                    "is_omitted": false,
                    "record_id": "29752-07",
                    "uuid": "4920c143-8179-4aca-b0a3-0c406454c4da"
                },
                {
                    "is_omitted": false,
                    "record_id": "29752-08",
                    "uuid": "c94dd0c4-c4b0-435a-8fbd-b706d48bc2fb"
                }
            ],
            "decay_constants": {
                "lambda_k_total": 5.463e-10,
                "lambda_k_total_error": 9.998499887483122e-12
            },
            "identifier": "29752",
            "j": 0.005772869064169085,
            "j_err": 3.2022500914947364e-06,
            "mean_j": 0.005772430662422862,
            "mean_j_err": 3.3307518039602716e-06,
            "mean_j_mswd": 2.4828242553210456,
            "options": {
                "interpolation_style": "Weighted Mean",
                "model_kind": "Bracketing",
                "monitor_age": 28.201,
                "monitor_material": "FC-2",
                "monitor_name": "FC-2",
                "monitor_reference": "FC Min",
                "monte_carlo_ntrials": 10,
                "predicted_j_error_type": "SE but if MSWD>1 use SE * sqrt(MSWD)",
                "use_monte_carlo": false,
                "use_weighted_fit": false
            },
            "position": 19,
            "position_jerr": 0.0
        },
        {
            "analyses": [],
            "decay_constants": {
                "lambda_k_total": 5.463e-10,
                "lambda_k_total_error": 9.998499887483122e-12
            },
            "identifier": "71424",
            "j": 0.005774643335612769,
            "j_err": 2.2109052311473815e-06,
            "mean_j": 0.0,
            "mean_j_err": 0.0,
            "mean_j_mswd": 0.0,
            "options": {
                "interpolation_style": "Weighted Mean",
                "model_kind": "Bracketing",
                "monitor_age": 28.201,
                "monitor_material": "FC-2",
                "monitor_name": "FC-2",
                "monitor_reference": "FC Min",
                "monte_carlo_ntrials": 10,
                "predicted_j_error_type": "SE but if MSWD>1 use SE * sqrt(MSWD)",
                "use_monte_carlo": false,
                "use_weighted_fit": false
            },
            "position": 20,
            "position_jerr": 0.0
        },
        {
            "analyses": [],
            "decay_constants": {
                "lambda_k_total": 5.463e-10,
                "lambda_k_total_error": 9.998499887483122e-12
            },
            "identifier": "71425",
            "j": 0.005774643335612769,
            "j_err": 2.2109052311473815e-06,
            "mean_j": 0.0,
            "mean_j_err": 0.0,
            "mean_j_mswd": 0.0,
            "options": {
                "interpolation_style": "Weighted Mean",
                "model_kind": "Bracketing",
                "monitor_age": 28.201,
                "monitor_material": "FC-2",
                "monitor_name": "FC-2",
                "monitor_reference": "FC Min",
                "monte_carlo_ntrials": 10,
                "predicted_j_error_type": "SE but if MSWD>1 use SE * sqrt(MSWD)",
                "use_monte_carlo": false,
                "use_weighted_fit": false
            },
            "position": 21,
            "position_jerr": 0.0
        },
        {
            "analyses": [
                {
                    "is_omitted": false,
                    "record_id": "29753-01",
                    "uuid": "40a82d6c-4f8b-4499-af02-9568acd1ba34"
                },
                {
                    "is_omitted": false,
                    "record_id": "29753-02",
                    "uuid": "0a8bea9a-2682-4be8-b0ae-7699702882db"
                },
                {
                    "is_omitted": false,
                    "record_id": "29753-03",
                    "uuid": "c9510b1d-78db-4de7-bc34-550a47c4710c"
                },
                {
                    "is_omitted": true,
                    "record_id": "29753-04",
                    "uuid": "e3c02b33-abe9-4f17-a119-7b7580497ac8"
                },
                {
                    "is_omitted": false,
                    "record_id": "29753-05",
                    "uuid": "373697d6-f070-4a79-b6d3-5587aef1b36f"
                },
                {
                    "is_omitted": false,
                    "record_id": "29753-06",
                    "uuid": "d1aebab2-7892-486a-93d0-705df2d10850"
                },
                {
                    "is_omitted": false,
                    "record_id": "29753-07",
                    "uuid": "d6f54e00-b07c-4039-985a-2df8f4b56dc8"
                },
                {
                    "is_omitted": false,
                    "record_id": "29753-08",
                    "uuid": "5a0a6830-6993-4f06-bcf0-01fcbf196967"
                }
            ],
            "decay_constants": {
                "lambda_k_total": 5.463e-10,
                "lambda_k_total_error": 9.998499887483122e-12
            },
            "identifier": "29753",
            "j": 0.00577708074908354,
            "j_err": 2.936667345696728e-06,
            "mean_j": 0.005776386182995484,
            "mean_j_err": 2.9560604723756245e-06,
            "mean_j_mswd": 2.1223762078370245,
            "options": {
                "interpolation_style": "Weighted Mean",
                "model_kind": "Bracketing",
                "monitor_age": 28.201,
                "monitor_material": "FC-2",
                "monitor_name": "FC-2",
                "monitor_reference": "FC Min",
                "monte_carlo_ntrials": 10,
                "predicted_j_error_type": "SE but if MSWD>1 use SE * sqrt(MSWD)",
                "use_monte_carlo": false,
                "use_weighted_fit": false
            },
            "position": 22,
            "position_jerr": 0.0
        },
        {
            "analyses": [],
            "decay_constants": {
                "lambda_k_total": 5.463e-10,
                "lambda_k_total_error": 9.998499887483122e-12
            },
            "identifier": "71426",
            "j": 0.00577708074908354,
            "j_err": 2.936667345696728e-06,
            "mean_j": 0.0,
            "mean_j_err": 0.0,
            "mean_j_mswd": 0.0,
            "options": {
                "interpolation_style": "Weighted Mean",
                "model_kind": "Bracketing",
                "monitor_age": 28.201,
                "monitor_material": "FC-2",
                "monitor_name": "FC-2",
                "monitor_reference": "FC Min",
                "monte_carlo_ntrials": 10,
                "predicted_j_error_type": "SE but if MSWD>1 use SE * sqrt(MSWD)",
                "use_monte_carlo": false,
                "use_weighted_fit": false
            },
            "position": 23,
            "position_jerr": 0.0
        },
        {
            "analyses": [],
            "decay_constants": {
                "lambda_k_total": 5.463e-10,
                "lambda_k_total_error": 9.998499887483122e-12
            },
            "identifier": "71427",
            "j": 0.00577708074908354,
            "j_err": 2.936667345696728e-06,
            "mean_j": 0.0,
            "mean_j_err": 0.0,
            "mean_j_mswd": 0.0,
            "options": {
                "interpolation_style": "Weighted Mean",
                "model_kind": "Bracketing",
                "monitor_age": 28.201,
                "monitor_material": "FC-2",
                "monitor_name": "FC-2",
                "monitor_reference": "FC Min",
                "monte_carlo_ntrials": 10,
                "predicted_j_error_type": "SE but if MSWD>1 use SE * sqrt(MSWD)",
                "use_monte_carlo": false,
                "use_weighted_fit": false
            },
            "position": 24,
            "position_jerr": 0.0
        }
    ],
    "z": 0.0
}