{
    "positions": [
        {
            "analyses": [
                {
                    "is_omitted": false,
                    "record_id": "31386-01",
                    "uuid": "832147f5-789d-4e61-8736-ca4e17edda9d"
                },
                {
                    "is_omitted": false,
                    "record_id": "31386-02",
                    "uuid": "251c551d-1883-465f-b832-68fb565634b1"
                },
                {
                    "is_omitted": false,
                    "record_id": "31386-03",
                    "uuid": "0a7c5338-26b8-476e-a401-b608c4bc3611"
                },
                {
                    "is_omitted": false,
                    "record_id": "31386-04",
                    "uuid": "640a03d2-ce63-4777-a24b-3db4a8f5a9b5"
                },
                {
                    "is_omitted": false,
                    "record_id": "31386-05",
                    "uuid": "e0c8bddc-ad53-4075-845c-e76d30c45620"
                },
                {
                    "is_omitted": true,
                    "record_id": "31386-06",
                    "uuid": "6d2c2e2b-7ffd-4e34-825a-72664cdc9c08"
                },
                {
                    "is_omitted": true,
                    "record_id": "31386-07",
                    "uuid": "ef87702a-4719-4591-b181-f7070ba561a2"
                },
                {
                    "is_omitted": true,
                    "record_id": "31386-08",
                    "uuid": "1cf84dd4-307a-4aa9-b83a-49b005669219"
                }
            ],
            "decay_constants": {
                "lambda_k_total": 5.463e-10,
                "lambda_k_total_error": 9.998499887483122e-12
            },
            "identifier": "31386",
            "j": 0.0018859982035381157,
            "j_err": 2.660277813363828e-07,
            "mean_j": 0.0018859688316346516,
            "mean_j_err": 2.696235973191333e-07,
            "mean_j_mswd": 0.10712244515034626,
            "options": {
                "interpolation_style": "Weighted Mean",
                "model_kind": "Bracketing",
                "monitor_age": 28.201,
                "monitor_material": "FC-2",
                "monitor_name": "FC-2",
                "monitor_reference": "FC Min",
                "monte_carlo_ntrials": 10000,
                "predicted_j_error_type": "SD",
                "use_monte_carlo": true,
                "use_weighted_fit": true
            },
            "position": 7,
            "position_jerr": 0.0
        },
        {
            "analyses": [
                {
                    "is_omitted": false,
                    "record_id": "31387-01",
                    "uuid": "5a2dd933-ca8e-4fae-a22a-05a6d0d38eee"
                },
                {
                    "is_omitted": false,
                    "record_id": "31387-02",
                    "uuid": "022f8a62-e50e-4d6e-a182-b7e06b690f0a"
                },
                {
                    "is_omitted": false,
                    "record_id": "31387-03",
                    "uuid": "d5a7b1c2-dfb9-4dd1-8153-302c45d20410"
                },
                {
                    "is_omitted": false,
                    "record_id": "31387-04",
                    "uuid": "6be5ad7e-301d-4ebe-9839-f6b9df00a30e"
                },
                {
                    "is_omitted": false,
                    "record_id": "31387-05",
                    "uuid": "781556af-b61a-4378-89c8-8c9efdb6a3f6"
                },
                {
                    "is_omitted": false,
                    "record_id": "31387-06",
                    "uuid": "d3eea6fc-888b-4486-adc4-27682cb3275a"
                },
                {
                    "is_omitted": false,
                    "record_id": "31387-07",
                    "uuid": "e71412d5-5c84-4543-a471-e219b3a6a2ea"
                },
                {
                    "is_omitted": false,
                    "record_id": "31387-08",
                    "uuid": "3d289882-c28b-4f13-ab61-e14d7509fba6"
                }
            ],
            "decay_constants": {
                "lambda_k_total": 5.463e-10,
                "lambda_k_total_error": 9.998499887483122e-12
            },
            "identifier": "31387",
            "j": 0.0018877446630273112,
            "j_err": 9.770457113900958e-07,
            "mean_j": 0.0018870774146084626,
            "mean_j_err": 1.6343499289181333e-06,
            "mean_j_mswd": 4.418307218295217,
            "options": {
                "interpolation_style": "Weighted Mean",
                "model_kind": "Bracketing",
                "monitor_age": 28.201,
                "monitor_material": "FC-2",
                "monitor_name": "FC-2",
                "monitor_reference": "FC Min",
                "monte_carlo_ntrials": 10000,
                "predicted_j_error_type": "SD",
                "use_monte_carlo": true,
                "use_weighted_fit": true
            },
            "position": 8,
            "position_jerr": 0.0
        },
        {
            "analyses": [
                {
                    "is_omitted": false,
                    "record_id": "31388-01",
                    "uuid": "32f975e0-d4ee-4e65-a1fa-14352a9934ae"
                },
                {
                    "is_omitted": false,
                    "record_id": "31388-02",
                    "uuid": "ae18b5d2-fc63-4e97-804d-9f8d5748c327"
                },
                {
                    "is_omitted": false,
                    "record_id": "31388-03",
                    "uuid": "1a218f20-f0d6-46b9-b016-a151fc7c5440"
                },
                {
                    "is_omitted": false,
                    "record_id": "31388-04",
                    "uuid": "59bc27be-d4e8-4956-a3e8-19100996c9c0"
                },
                {
                    "is_omitted": false,
                    "record_id": "31388-05",
                    "uuid": "43c950a6-83f1-4c4f-ab01-6c224f045017"
                },
                {
                    "is_omitted": false,
                    "record_id": "31388-06",
                    "uuid": "fbe2dec1-e969-40f5-a307-83cf90bafe23"
                },
                {
                    "is_omitted": false,
                    "record_id": "31388-07",
                    "uuid": "3a37e30c-5abe-4f4c-8ecd-c42400ad5c9f"
                },
                {
                    "is_omitted": false,
                    "record_id": "31388-08",
                    "uuid": "fa1f9258-f380-4a01-a278-72045361cf4e"
                }
            ],
            "decay_constants": {
                "lambda_k_total": 5.463e-10,
                "lambda_k_total_error": 9.998499887483122e-12
            },
            "identifier": "31388",
            "j": 0.0018877446630273112,
            "j_err": 9.770457113900958e-07,
            "mean_j": 0.0018881157521506346,
            "mean_j_err": 1.218822279899429e-06,
            "mean_j_mswd": 1.7928835159904317,
            "options": {
                "interpolation_style": "Weighted Mean",
                "model_kind": "Bracketing",
                "monitor_age": 28.201,
                "monitor_material": "FC-2",
                "monitor_name": "FC-2",
                "monitor_reference": "FC Min",
                "monte_carlo_ntrials": 10000,
                "predicted_j_error_type": "SD",
                "use_monte_carlo": true,
                "use_weighted_fit": true
            },
            "position": 9,
            "position_jerr": 0.0
        },
        {
            "analyses": [
                {
                    "is_omitted": true,
                    "record_id": "31389-01",
                    "uuid": "42f09e8a-ab92-490a-b2dc-7285cf1051f6"
                },
                {
                    "is_omitted": false,
                    "record_id": "31389-02",
                    "uuid": "68200989-0862-408e-a8ad-304b91fff802"
                },
                {
                    "is_omitted": false,
                    "record_id": "31389-03",
                    "uuid": "83bbb660-65de-427e-9c81-861ff4bef23c"
                },
                {
                    "is_omitted": false,
                    "record_id": "31389-04",
                    "uuid": "d09cf4de-11a8-486a-8834-e9701376748b"
                },
                {
                    "is_omitted": false,
                    "record_id": "31389-05",
                    "uuid": "09d13950-73bb-4809-a4cc-f00707e82dfa"
                },
                {
                    "is_omitted": false,
                    "record_id": "31389-06",
                    "uuid": "9c11ac28-b237-4fc7-bd0f-842dedb1d474"
                },
                {
                    "is_omitted": false,
                    "record_id": "31389-07",
                    "uuid": "9113929c-510c-44a4-9066-388230c4a4fc"
                },
                {
                    "is_omitted": false,
                    "record_id": "31389-08",
                    "uuid": "6f236c8f-02b3-4d6e-a17c-1b1e798b0d8a"
                }
            ],
            "decay_constants": {
                "lambda_k_total": 5.463e-10,
                "lambda_k_total_error": 9.998499887483122e-12
            },
            "identifier": "31389",
            "j": 0.001888318139816663,
            "j_err": 9.629200654445699e-07,
            "mean_j": 0.0018886542541325189,
            "mean_j_err": 1.5706950267624489e-06,
            "mean_j_mswd": 3.3797163275747732,
            "options": {
                "interpolation_style": "Weighted Mean",
                "model_kind": "Bracketing",
                "monitor_age": 28.201,
                "monitor_material": "FC-2",
                "monitor_name": "FC-2",
                "monitor_reference": "FC Min",
                "monte_carlo_ntrials": 10000,
                "predicted_j_error_type": "SD",
                "use_monte_carlo": true,
                "use_weighted_fit": true
            },
            "position": 10,
            "position_jerr": 0.0
        },
        {
            "analyses": [
                {
                    "is_omitted": true,
                    "record_id": "31390-01",
                    "uuid": "94433d18-2dc1-4d7b-8a2f-93016f859d45"
                },
                {
                    "is_omitted": false,
                    "record_id": "31390-02",
                    "uuid": "755f99f5-e18a-486f-b05b-665f58504663"
                },
                {
                    "is_omitted": false,
                    "record_id": "31390-03",
                    "uuid": "4a503ead-930f-4cca-8bb3-be2860483fac"
                },
                {
                    "is_omitted": false,
                    "record_id": "31390-04",
                    "uuid": "c3036dbf-3940-49a0-8c60-f8f9ce3aa7c5"
                },
                {
                    "is_omitted": true,
                    "record_id": "31390-05",
                    "uuid": "fcb802ab-2d22-495b-b57a-7c66b546d332"
                },
                {
                    "is_omitted": false,
                    "record_id": "31390-06",
                    "uuid": "21990aa1-a13e-4c16-9a22-459c87f22564"
                },
                {
                    "is_omitted": false,
                    "record_id": "31390-07",
                    "uuid": "0420b99a-e587-4152-b2c3-2d17ebf58aaa"
                },
                {
                    "is_omitted": false,
                    "record_id": "31390-08",
                    "uuid": "f15f97f8-794b-4c13-95cd-5471591a5fc1"
                }
            ],
            "decay_constants": {
                "lambda_k_total": 5.463e-10,
                "lambda_k_total_error": 9.998499887483122e-12
            },
            "identifier": "31390",
            "j": 0.0018861140128689834,
            "j_err": 6.498528834418816e-07,
            "mean_j": 0.0018862819750864153,
            "mean_j_err": 9.118407612835734e-07,
            "mean_j_mswd": 1.1781302442903872,
            "options": {
                "interpolation_style": "Weighted Mean",
                "model_kind": "Bracketing",
                "monitor_age": 28.201,
                "monitor_material": "FC-2",
                "monitor_name": "FC-2",
                "monitor_reference": "FC Min",
                "monte_carlo_ntrials": 10000,
                "predicted_j_error_type": "SD",
                "use_monte_carlo": true,
                "use_weighted_fit": true
            },
            "position": 11,
            "position_jerr": 0.0
        },
        {
            "analyses": [
                {
                    "is_omitted": true,
                    "record_id": "31391-01",
                    "uuid": "0f6089d4-a450-4f51-bc61-98e189a68ee8"
                },
                {
                    "is_omitted": false,
                    "record_id": "31391-02",
                    "uuid": "4f0cdbb6-7607-4952-af3d-a737b7dcca1d"
                },
                {
                    "is_omitted": false,
                    "record_id": "31391-03",
                    "uuid": "c1846f77-4205-4442-aa75-b78619cf16d7"
                },
                {
                    "is_omitted": false,
                    "record_id": "31391-04",
                    "uuid": "1b9b2fc4-84ae-466c-927e-e583d8adcd68"
                },
                {
                    "is_omitted": false,
                    "record_id": "31391-05",
                    "uuid": "ed5cf8da-dae2-41eb-a689-0b82a5a759c3"
                },
                {
                    "is_omitted": false,
                    "record_id": "31391-06",
                    "uuid": "7fd57797-87c1-48b4-b49a-22aa9060bbad"
                },
                {
                    "is_omitted": false,
                    "record_id": "31391-07",
                    "uuid": "dedcf97a-df0e-468e-a144-b0c66a69c8e4"
                },
                {
                    "is_omitted": false,
                    "record_id": "31391-08",
                    "uuid": "acc0ea34-b303-492d-90a5-c293f2eec2d5"
                }
            ],
            "decay_constants": {
                "lambda_k_total": 5.463e-10,
                "lambda_k_total_error": 9.998499887483122e-12
            },
            "identifier": "31391",
            "j": 0.0018861140128689834,
            "j_err": 6.498528834418816e-07,
            "mean_j": 0.0018859406465771295,
            "mean_j_err": 9.263935710771817e-07,
            "mean_j_mswd": 0.9935964564718239,
            "options": {
                "interpolation_style": "Weighted Mean",
                "model_kind": "Bracketing",
                "monitor_age": 28.201,
                "monitor_material": "FC-2",
                "monitor_name": "FC-2",
                "monitor_reference": "FC Min",
                "monte_carlo_ntrials": 10000,
                "predicted_j_error_type": "SD",
                "use_monte_carlo": true,
                "use_weighted_fit": true
            },
            "position": 12,
            "position_jerr": 0.0
        },
        {
            "analyses": [],
            "decay_constants": {
                "lambda_k_total": 5.463e-10,
                "lambda_k_total_error": 9.998499887483122e-12
            },
            "identifier": "73164",
            "j": 0.0018859982035381157,
            "j_err": 2.660277813363828e-07,
            "mean_j": 0.0,
            "mean_j_err": 0.0,
            "mean_j_mswd": 0.0,
            "options": {
                "interpolation_style": "Weighted Mean",
                "model_kind": "Bracketing",
                "monitor_age": 28.201,
                "monitor_material": "FC-2",
                "monitor_name": "FC-2",
                "monitor_reference": "FC Min",
                "monte_carlo_ntrials": 10000,
                "predicted_j_error_type": "SD",
                "use_monte_carlo": true,
                "use_weighted_fit": true
            },
            "position": 1,
            "position_jerr": 0.0
        },
        {
            "analyses": [],
            "decay_constants": {
                "lambda_k_total": 5.463e-10,
                "lambda_k_total_error": 9.998499887483122e-12
            },
            "identifier": "73165",
            "j": 0.0018877446630273112,
            "j_err": 9.770457113900958e-07,
            "mean_j": 0.0,
            "mean_j_err": 0.0,
            "mean_j_mswd": 0.0,
            "options": {
                "interpolation_style": "Weighted Mean",
                "model_kind": "Bracketing",
                "monitor_age": 28.201,
                "monitor_material": "FC-2",
                "monitor_name": "FC-2",
                "monitor_reference": "FC Min",
                "monte_carlo_ntrials": 10000,
                "predicted_j_error_type": "SD",
                "use_monte_carlo": true,
                "use_weighted_fit": true
            },
            "position": 2,
            "position_jerr": 0.0
        },
        {
            "analyses": [],
            "decay_constants": {
                "lambda_k_total": 5.463e-10,
                "lambda_k_total_error": 9.998499887483122e-12
            },
            "identifier": "73166",
            "j": 0.001888318139816663,
            "j_err": 9.629200654445699e-07,
            "mean_j": 0.0,
            "mean_j_err": 0.0,
            "mean_j_mswd": 0.0,
            "options": {
                "interpolation_style": "Weighted Mean",
                "model_kind": "Bracketing",
                "monitor_age": 28.201,
                "monitor_material": "FC-2",
                "monitor_name": "FC-2",
                "monitor_reference": "FC Min",
                "monte_carlo_ntrials": 10000,
                "predicted_j_error_type": "SD",
                "use_monte_carlo": true,
                "use_weighted_fit": true
            },
            "position": 3,
            "position_jerr": 0.0
        },
        {
            "analyses": [],
            "decay_constants": {
                "lambda_k_total": 5.463e-10,
                "lambda_k_total_error": 9.998499887483122e-12
            },
            "identifier": "73167",
            "j": 0.0018868799493475825,
            "j_err": 7.885881154512688e-07,
            "mean_j": 0.0,
            "mean_j_err": 0.0,
            "mean_j_mswd": 0.0,
            "options": {
                "interpolation_style": "Weighted Mean",
                "model_kind": "Bracketing",
                "monitor_age": 28.201,
                "monitor_material": "FC-2",
                "monitor_name": "FC-2",
                "monitor_reference": "FC Min",
                "monte_carlo_ntrials": 10000,
                "predicted_j_error_type": "SD",
                "use_monte_carlo": true,
                "use_weighted_fit": true
            },
            "position": 4,
            "position_jerr": 0.0
        },
        {
            "analyses": [],
            "decay_constants": {
                "lambda_k_total": 5.463e-10,
                "lambda_k_total_error": 9.998499887483122e-12
            },
            "identifier": "73168",
            "j": 0.0018861140128689834,
            "j_err": 6.498528834418816e-07,
            "mean_j": 0.0,
            "mean_j_err": 0.0,
            "mean_j_mswd": 0.0,
            "options": {
                "interpolation_style": "Weighted Mean",
                "model_kind": "Bracketing",
                "monitor_age": 28.201,
                "monitor_material": "FC-2",
                "monitor_name": "FC-2",
                "monitor_reference": "FC Min",
                "monte_carlo_ntrials": 10000,
                "predicted_j_error_type": "SD",
                "use_monte_carlo": true,
                "use_weighted_fit": true
            },
            "position": 5,
            "position_jerr": 0.0
        },
        {
            "analyses": [],
            "decay_constants": {
                "lambda_k_total": 5.463e-10,
                "lambda_k_total_error": 9.998499887483122e-12
            },
            "identifier": "73169",
            "j": 0.0018859666305801781,
            "j_err": 2.5888176762048584e-07,
            "mean_j": 0.0,
            "mean_j_err": 0.0,
            "mean_j_mswd": 0.0,
            "options": {
                "interpolation_style": "Weighted Mean",
                "model_kind": "Bracketing",
                "monitor_age": 28.201,
                "monitor_material": "FC-2",
                "monitor_name": "FC-2",
                "monitor_reference": "FC Min",
                "monte_carlo_ntrials": 10000,
                "predicted_j_error_type": "SD",
                "use_monte_carlo": true,
                "use_weighted_fit": true
            },
            "position": 6,
            "position_jerr": 0.0
        }
    ],
    "z": 0.0
}