{
    "positions": [
        {
            "analyses": [],
            "decay_constants": {},
            "identifier": "69811",
            "j": 0.004037224080107221,
            "j_err": 4.328212952810974e-07,
            "mean_j": 0,
            "mean_j_err": 0,
            "mean_j_mswd": 0,
            "options": {},
            "position": 1,
            "position_jerr": null
        },
        {
            "analyses": [],
            "decay_constants": {},
            "identifier": "69812",
            "j": 0.004037257548327474,
            "j_err": 4.3020799568124204e-07,
            "mean_j": 0,
            "mean_j_err": 0,
            "mean_j_mswd": 0,
            "options": {},
            "position": 2,
            "position_jerr": null
        },
        {
            "analyses": [],
            "decay_constants": {},
            "identifier": "69813",
            "j": 0.004039895154561361,
            "j_err": 4.3203415457291664e-07,
            "mean_j": 0,
            "mean_j_err": 0,
            "mean_j_mswd": 0,
            "options": {},
            "position": 3,
            "position_jerr": null
        },
        {
            "analyses": [],
            "decay_constants": {},
            "identifier": "69814",
            "j": 0.004045080594536941,
            "j_err": 4.3972730502224536e-07,
            "mean_j": 0,
            "mean_j_err": 0,
            "mean_j_mswd": 0,
            "options": {},
            "position": 4,
            "position_jerr": null
        },
        {
            "analyses": [],
            "decay_constants": {},
            "identifier": "69815",
            "j": 0.004052697545431031,
            "j_err": 4.4804791835926146e-07,
            "mean_j": 0,
            "mean_j_err": 0,
            "mean_j_mswd": 0,
            "options": {},
            "position": 5,
            "position_jerr": null
        },
        {
            "analyses": [],
            "decay_constants": {},
            "identifier": "69816",
            "j": 0.004062573633346257,
            "j_err": 4.569212698561305e-07,
            "mean_j": 0,
            "mean_j_err": 0,
            "mean_j_mswd": 0,
            "options": {},
            "position": 6,
            "position_jerr": null
        },
        {
            "analyses": [],
            "decay_constants": {},
            "identifier": "69817",
            "j": 0.004074506475109626,
            "j_err": 4.6759958924106555e-07,
            "mean_j": 0,
            "mean_j_err": 0,
            "mean_j_mswd": 0,
            "options": {},
            "position": 7,
            "position_jerr": null
        },
        {
            "analyses": [],
            "decay_constants": {},
            "identifier": "69818",
            "j": 0.004088263678272523,
            "j_err": 4.835240808156769e-07,
            "mean_j": 0,
            "mean_j_err": 0,
            "mean_j_mswd": 0,
            "options": {},
            "position": 8,
            "position_jerr": null
        },
        {
            "analyses": [],
            "decay_constants": {},
            "identifier": "69819",
            "j": 0.004103520838820946,
            "j_err": 4.926800489481938e-07,
            "mean_j": 0,
            "mean_j_err": 0,
            "mean_j_mswd": 0,
            "options": {},
            "position": 9,
            "position_jerr": null
        },
        {
            "analyses": [],
            "decay_constants": {},
            "identifier": "69820",
            "j": 0.004119957520217944,
            "j_err": 5.014416752501006e-07,
            "mean_j": 0,
            "mean_j_err": 0,
            "mean_j_mswd": 0,
            "options": {},
            "position": 10,
            "position_jerr": null
        },
        {
            "analyses": [],
            "decay_constants": {},
            "identifier": "69821",
            "j": 0.00413721732543537,
            "j_err": 5.065562471723722e-07,
            "mean_j": 0,
            "mean_j_err": 0,
            "mean_j_mswd": 0,
            "options": {},
            "position": 11,
            "position_jerr": null
        },
        {
            "analyses": [],
            "decay_constants": {},
            "identifier": "69822",
            "j": 0.0041549679155051256,
            "j_err": 5.141907206287949e-07,
            "mean_j": 0,
            "mean_j_err": 0,
            "mean_j_mswd": 0,
            "options": {},
            "position": 12,
            "position_jerr": null
        },
        {
            "analyses": [],
            "decay_constants": {},
            "identifier": "69823",
            "j": 0.0041727889073707725,
            "j_err": 5.212841382794949e-07,
            "mean_j": 0,
            "mean_j_err": 0,
            "mean_j_mswd": 0,
            "options": {},
            "position": 13,
            "position_jerr": null
        },
        {
            "analyses": [],
            "decay_constants": {},
            "identifier": "69824",
            "j": 0.004190343994587162,
            "j_err": 5.272373834478703e-07,
            "mean_j": 0,
            "mean_j_err": 0,
            "mean_j_mswd": 0,
            "options": {},
            "position": 14,
            "position_jerr": null
        },
        {
            "analyses": [],
            "decay_constants": {},
            "identifier": "69825",
            "j": 0.004207202875405233,
            "j_err": 5.337675079671774e-07,
            "mean_j": 0,
            "mean_j_err": 0,
            "mean_j_mswd": 0,
            "options": {},
            "position": 15,
            "position_jerr": null
        },
        {
            "analyses": [],
            "decay_constants": {},
            "identifier": "69826",
            "j": 0.004223049333962834,
            "j_err": 5.394313882584161e-07,
            "mean_j": 0,
            "mean_j_err": 0,
            "mean_j_mswd": 0,
            "options": {},
            "position": 16,
            "position_jerr": null
        },
        {
            "analyses": [],
            "decay_constants": {},
            "identifier": "69827",
            "j": 0.0042375311939066174,
            "j_err": 5.489816378446665e-07,
            "mean_j": 0,
            "mean_j_err": 0,
            "mean_j_mswd": 0,
            "options": {},
            "position": 17,
            "position_jerr": null
        },
        {
            "analyses": [],
            "decay_constants": {},
            "identifier": "69828",
            "j": 0.004250352329957427,
            "j_err": 5.53495683053592e-07,
            "mean_j": 0,
            "mean_j_err": 0,
            "mean_j_mswd": 0,
            "options": {},
            "position": 18,
            "position_jerr": null
        },
        {
            "analyses": [],
            "decay_constants": {},
            "identifier": "69829",
            "j": 0.004261240674896153,
            "j_err": 5.624120340886961e-07,
            "mean_j": 0,
            "mean_j_err": 0,
            "mean_j_mswd": 0,
            "options": {},
            "position": 19,
            "position_jerr": null
        },
        {
            "analyses": [],
            "decay_constants": {},
            "identifier": "69830",
            "j": 0.0042699201940266385,
            "j_err": 5.699903952458624e-07,
            "mean_j": 0,
            "mean_j_err": 0,
            "mean_j_mswd": 0,
            "options": {},
            "position": 20,
            "position_jerr": null
        },
        {
            "analyses": [],
            "decay_constants": {},
            "identifier": "69831",
            "j": 0.004276254980338202,
            "j_err": 5.792265252893861e-07,
            "mean_j": 0,
            "mean_j_err": 0,
            "mean_j_mswd": 0,
            "options": {},
            "position": 21,
            "position_jerr": null
        },
        {
            "analyses": [],
            "decay_constants": {},
            "identifier": "69832",
            "j": 0.004280107143081639,
            "j_err": 5.875797321549101e-07,
            "mean_j": 0,
            "mean_j_err": 0,
            "mean_j_mswd": 0,
            "options": {},
            "position": 22,
            "position_jerr": null
        },
        {
            "analyses": [],
            "decay_constants": {},
            "identifier": "69833",
            "j": 0.0042813688007833665,
            "j_err": 5.940844179369542e-07,
            "mean_j": 0,
            "mean_j_err": 0,
            "mean_j_mswd": 0,
            "options": {},
            "position": 23,
            "position_jerr": null
        },
        {
            "analyses": [],
            "decay_constants": {},
            "identifier": "69834",
            "j": 0.004280008213626988,
            "j_err": 6.023246986393396e-07,
            "mean_j": 0,
            "mean_j_err": 0,
            "mean_j_mswd": 0,
            "options": {},
            "position": 24,
            "position_jerr": null
        },
        {
            "analyses": [],
            "decay_constants": {},
            "identifier": "69835",
            "j": 0.004276085653361494,
            "j_err": 6.086612679367093e-07,
            "mean_j": 0,
            "mean_j_err": 0,
            "mean_j_mswd": 0,
            "options": {},
            "position": 25,
            "position_jerr": null
        },
        {
            "analyses": [],
            "decay_constants": {},
            "identifier": "69836",
            "j": 0.004269687433534446,
            "j_err": 6.156359659976144e-07,
            "mean_j": 0,
            "mean_j_err": 0,
            "mean_j_mswd": 0,
            "options": {},
            "position": 26,
            "position_jerr": null
        },
        {
            "analyses": [],
            "decay_constants": {},
            "identifier": "69837",
            "j": 0.004260901851431931,
            "j_err": 6.248005350335669e-07,
            "mean_j": 0,
            "mean_j_err": 0,
            "mean_j_mswd": 0,
            "options": {},
            "position": 27,
            "position_jerr": null
        },
        {
            "analyses": [],
            "decay_constants": {},
            "identifier": "69838",
            "j": 0.004249957332025514,
            "j_err": 6.26534548923615e-07,
            "mean_j": 0,
            "mean_j_err": 0,
            "mean_j_mswd": 0,
            "options": {},
            "position": 28,
            "position_jerr": null
        },
        {
            "analyses": [],
            "decay_constants": {},
            "identifier": "69839",
            "j": 0.00423708626776381,
            "j_err": 6.218787108299631e-07,
            "mean_j": 0,
            "mean_j_err": 0,
            "mean_j_mswd": 0,
            "options": {},
            "position": 29,
            "position_jerr": null
        },
        {
            "analyses": [],
            "decay_constants": {},
            "identifier": "69840",
            "j": 0.00422255304410958,
            "j_err": 6.202148773958657e-07,
            "mean_j": 0,
            "mean_j_err": 0,
            "mean_j_mswd": 0,
            "options": {},
            "position": 30,
            "position_jerr": null
        },
        {
            "analyses": [],
            "decay_constants": {},
            "identifier": "69841",
            "j": 0.004206678097599774,
            "j_err": 6.1351074110052e-07,
            "mean_j": 0,
            "mean_j_err": 0,
            "mean_j_mswd": 0,
            "options": {},
            "position": 31,
            "position_jerr": null
        },
        {
            "analyses": [],
            "decay_constants": {},
            "identifier": "69842",
            "j": 0.004189761774188346,
            "j_err": 6.010322555962213e-07,
            "mean_j": 0,
            "mean_j_err": 0,
            "mean_j_mswd": 0,
            "options": {},
            "position": 32,
            "position_jerr": null
        },
        {
            "analyses": [],
            "decay_constants": {},
            "identifier": "69843",
            "j": 0.004172214538239113,
            "j_err": 5.912086912875573e-07,
            "mean_j": 0,
            "mean_j_err": 0,
            "mean_j_mswd": 0,
            "options": {},
            "position": 33,
            "position_jerr": null
        },
        {
            "analyses": [],
            "decay_constants": {},
            "identifier": "69844",
            "j": 0.00415437269619722,
            "j_err": 5.780458898359325e-07,
            "mean_j": 0,
            "mean_j_err": 0,
            "mean_j_mswd": 0,
            "options": {},
            "position": 34,
            "position_jerr": null
        },
        {
            "analyses": [],
            "decay_constants": {},
            "identifier": "69845",
            "j": 0.004136656631119106,
            "j_err": 5.621549642439028e-07,
            "mean_j": 0,
            "mean_j_err": 0,
            "mean_j_mswd": 0,
            "options": {},
            "position": 35,
            "position_jerr": null
        },
        {
            "analyses": [],
            "decay_constants": {},
            "identifier": "69846",
            "j": 0.0041194066169269695,
            "j_err": 5.458655384818314e-07,
            "mean_j": 0,
            "mean_j_err": 0,
            "mean_j_mswd": 0,
            "options": {},
            "position": 36,
            "position_jerr": null
        },
        {
            "analyses": [],
            "decay_constants": {},
            "identifier": "69847",
            "j": 0.004102994920557154,
            "j_err": 5.263711649225014e-07,
            "mean_j": 0,
            "mean_j_err": 0,
            "mean_j_mswd": 0,
            "options": {},
            "position": 37,
            "position_jerr": null
        },
        {
            "analyses": [],
            "decay_constants": {},
            "identifier": "69848",
            "j": 0.004087773718363008,
            "j_err": 5.081576496363552e-07,
            "mean_j": 0,
            "mean_j_err": 0,
            "mean_j_mswd": 0,
            "options": {},
            "position": 38,
            "position_jerr": null
        },
        {
            "analyses": [],
            "decay_constants": {},
            "identifier": "69849",
            "j": 0.004074091219220829,
            "j_err": 4.888779491084914e-07,
            "mean_j": 0,
            "mean_j_err": 0,
            "mean_j_mswd": 0,
            "options": {},
            "position": 39,
            "position_jerr": null
        },
        {
            "analyses": [],
            "decay_constants": {},
            "identifier": "69850",
            "j": 0.004062219490349726,
            "j_err": 4.6704615163003746e-07,
            "mean_j": 0,
            "mean_j_err": 0,
            "mean_j_mswd": 0,
            "options": {},
            "position": 40,
            "position_jerr": null
        },
        {
            "analyses": [],
            "decay_constants": {},
            "identifier": "69851",
            "j": 0.004052404557170238,
            "j_err": 4.563055851437611e-07,
            "mean_j": 0,
            "mean_j_err": 0,
            "mean_j_mswd": 0,
            "options": {},
            "position": 41,
            "position_jerr": null
        },
        {
            "analyses": [],
            "decay_constants": {},
            "identifier": "69852",
            "j": 0.00404486640330433,
            "j_err": 4.47139503740896e-07,
            "mean_j": 0,
            "mean_j_err": 0,
            "mean_j_mswd": 0,
            "options": {},
            "position": 42,
            "position_jerr": null
        },
        {
            "analyses": [],
            "decay_constants": {},
            "identifier": "69853",
            "j": 0.00403976896129978,
            "j_err": 4.366931077355479e-07,
            "mean_j": 0,
            "mean_j_err": 0,
            "mean_j_mswd": 0,
            "options": {},
            "position": 43,
            "position_jerr": null
        },
        {
            "analyses": [],
            "decay_constants": {},
            "identifier": "69854",
            "j": 0.0040540394023646925,
            "j_err": 3.7732366535431865e-07,
            "mean_j": 0,
            "mean_j_err": 0,
            "mean_j_mswd": 0,
            "options": {},
            "position": 44,
            "position_jerr": null
        },
        {
            "analyses": [],
            "decay_constants": {},
            "identifier": "69855",
            "j": 0.004054295091143188,
            "j_err": 3.785403743892115e-07,
            "mean_j": 0,
            "mean_j_err": 0,
            "mean_j_mswd": 0,
            "options": {},
            "position": 45,
            "position_jerr": null
        },
        {
            "analyses": [],
            "decay_constants": {},
            "identifier": "69856",
            "j": 0.0040575591778858056,
            "j_err": 3.808752763955436e-07,
            "mean_j": 0,
            "mean_j_err": 0,
            "mean_j_mswd": 0,
            "options": {},
            "position": 46,
            "position_jerr": null
        },
        {
            "analyses": [],
            "decay_constants": {},
            "identifier": "69857",
            "j": 0.004063751300260559,
            "j_err": 3.873658961543925e-07,
            "mean_j": 0,
            "mean_j_err": 0,
            "mean_j_mswd": 0,
            "options": {},
            "position": 47,
            "position_jerr": null
        },
        {
            "analyses": [],
            "decay_constants": {},
            "identifier": "69858",
            "j": 0.004072682961264127,
            "j_err": 3.9772084111384956e-07,
            "mean_j": 0,
            "mean_j_err": 0,
            "mean_j_mswd": 0,
            "options": {},
            "position": 48,
            "position_jerr": null
        },
        {
            "analyses": [],
            "decay_constants": {},
            "identifier": "69859",
            "j": 0.004084103661603423,
            "j_err": 4.0925032179742005e-07,
            "mean_j": 0,
            "mean_j_err": 0,
            "mean_j_mswd": 0,
            "options": {},
            "position": 49,
            "position_jerr": null
        },
        {
            "analyses": [],
            "decay_constants": {},
            "identifier": "69860",
            "j": 0.0040977028834341175,
            "j_err": 4.2415772902545194e-07,
            "mean_j": 0,
            "mean_j_err": 0,
            "mean_j_mswd": 0,
            "options": {},
            "position": 50,
            "position_jerr": null
        },
        {
            "analyses": [],
            "decay_constants": {},
            "identifier": "69861",
            "j": 0.004113052055547926,
            "j_err": 4.3201176142590484e-07,
            "mean_j": 0,
            "mean_j_err": 0,
            "mean_j_mswd": 0,
            "options": {},
            "position": 51,
            "position_jerr": null
        },
        {
            "analyses": [],
            "decay_constants": {},
            "identifier": "69862",
            "j": 0.004129722606736564,
            "j_err": 4.4346705761659923e-07,
            "mean_j": 0,
            "mean_j_err": 0,
            "mean_j_mswd": 0,
            "options": {},
            "position": 52,
            "position_jerr": null
        },
        {
            "analyses": [],
            "decay_constants": {},
            "identifier": "69863",
            "j": 0.004147246037823502,
            "j_err": 4.5191056577513484e-07,
            "mean_j": 0,
            "mean_j_err": 0,
            "mean_j_mswd": 0,
            "options": {},
            "position": 53,
            "position_jerr": null
        },
        {
            "analyses": [],
            "decay_constants": {},
            "identifier": "69864",
            "j": 0.004165095814819494,
            "j_err": 4.6120961435904886e-07,
            "mean_j": 0,
            "mean_j_err": 0,
            "mean_j_mswd": 0,
            "options": {},
            "position": 54,
            "position_jerr": null
        },
        {
            "analyses": [],
            "decay_constants": {},
            "identifier": "69865",
            "j": 0.004182793519855386,
            "j_err": 4.7167060261981737e-07,
            "mean_j": 0,
            "mean_j_err": 0,
            "mean_j_mswd": 0,
            "options": {},
            "position": 55,
            "position_jerr": null
        },
        {
            "analyses": [],
            "decay_constants": {},
            "identifier": "69866",
            "j": 0.004199798732772261,
            "j_err": 4.781078582719949e-07,
            "mean_j": 0,
            "mean_j_err": 0,
            "mean_j_mswd": 0,
            "options": {},
            "position": 56,
            "position_jerr": null
        },
        {
            "analyses": [],
            "decay_constants": {},
            "identifier": "69867",
            "j": 0.0042156511425454355,
            "j_err": 4.860527008317652e-07,
            "mean_j": 0,
            "mean_j_err": 0,
            "mean_j_mswd": 0,
            "options": {},
            "position": 57,
            "position_jerr": null
        },
        {
            "analyses": [],
            "decay_constants": {},
            "identifier": "69868",
            "j": 0.004229880519457607,
            "j_err": 4.974894512247424e-07,
            "mean_j": 0,
            "mean_j_err": 0,
            "mean_j_mswd": 0,
            "options": {},
            "position": 58,
            "position_jerr": null
        },
        {
            "analyses": [],
            "decay_constants": {},
            "identifier": "69869",
            "j": 0.004242044659328566,
            "j_err": 5.047066816639968e-07,
            "mean_j": 0,
            "mean_j_err": 0,
            "mean_j_mswd": 0,
            "options": {},
            "position": 59,
            "position_jerr": null
        },
        {
            "analyses": [],
            "decay_constants": {},
            "identifier": "69870",
            "j": 0.004251833550709483,
            "j_err": 5.118913149661599e-07,
            "mean_j": 0,
            "mean_j_err": 0,
            "mean_j_mswd": 0,
            "options": {},
            "position": 60,
            "position_jerr": null
        },
        {
            "analyses": [],
            "decay_constants": {},
            "identifier": "69871",
            "j": 0.004258965207688627,
            "j_err": 5.201005044415615e-07,
            "mean_j": 0,
            "mean_j_err": 0,
            "mean_j_mswd": 0,
            "options": {},
            "position": 61,
            "position_jerr": null
        },
        {
            "analyses": [],
            "decay_constants": {},
            "identifier": "69872",
            "j": 0.004263235769749976,
            "j_err": 5.314431464413049e-07,
            "mean_j": 0,
            "mean_j_err": 0,
            "mean_j_mswd": 0,
            "options": {},
            "position": 62,
            "position_jerr": null
        },
        {
            "analyses": [],
            "decay_constants": {},
            "identifier": "69873",
            "j": 0.004264497427451703,
            "j_err": 5.370636984157513e-07,
            "mean_j": 0,
            "mean_j_err": 0,
            "mean_j_mswd": 0,
            "options": {},
            "position": 63,
            "position_jerr": null
        },
        {
            "analyses": [],
            "decay_constants": {},
            "identifier": "69874",
            "j": 0.004262714473500363,
            "j_err": 5.448602077918641e-07,
            "mean_j": 0,
            "mean_j_err": 0,
            "mean_j_mswd": 0,
            "options": {},
            "position": 64,
            "position_jerr": null
        },
        {
            "analyses": [],
            "decay_constants": {},
            "identifier": "69875",
            "j": 0.004257963302750894,
            "j_err": 5.512863346679764e-07,
            "mean_j": 0,
            "mean_j_err": 0,
            "mean_j_mswd": 0,
            "options": {},
            "position": 65,
            "position_jerr": null
        },
        {
            "analyses": [],
            "decay_constants": {},
            "identifier": "69876",
            "j": 0.0042503763611324245,
            "j_err": 5.593298317563197e-07,
            "mean_j": 0,
            "mean_j_err": 0,
            "mean_j_mswd": 0,
            "options": {},
            "position": 66,
            "position_jerr": null
        },
        {
            "analyses": [],
            "decay_constants": {},
            "identifier": "69877",
            "j": 0.004240176122400946,
            "j_err": 5.645910866614484e-07,
            "mean_j": 0,
            "mean_j_err": 0,
            "mean_j_mswd": 0,
            "options": {},
            "position": 67,
            "position_jerr": null
        },
        {
            "analyses": [],
            "decay_constants": {},
            "identifier": "69878",
            "j": 0.004227613085849546,
            "j_err": 5.588404395845692e-07,
            "mean_j": 0,
            "mean_j_err": 0,
            "mean_j_mswd": 0,
            "options": {},
            "position": 68,
            "position_jerr": null
        },
        {
            "analyses": [],
            "decay_constants": {},
            "identifier": "69879",
            "j": 0.00421308581341089,
            "j_err": 5.551858508092204e-07,
            "mean_j": 0,
            "mean_j_err": 0,
            "mean_j_mswd": 0,
            "options": {},
            "position": 69,
            "position_jerr": null
        },
        {
            "analyses": [],
            "decay_constants": {},
            "identifier": "69880",
            "j": 0.004197020892554737,
            "j_err": 5.476875531948598e-07,
            "mean_j": 0,
            "mean_j_err": 0,
            "mean_j_mswd": 0,
            "options": {},
            "position": 70,
            "position_jerr": null
        },
        {
            "analyses": [],
            "decay_constants": {},
            "identifier": "69881",
            "j": 0.004179854829443472,
            "j_err": 5.352664953009673e-07,
            "mean_j": 0,
            "mean_j_err": 0,
            "mean_j_mswd": 0,
            "options": {},
            "position": 71,
            "position_jerr": null
        },
        {
            "analyses": [],
            "decay_constants": {},
            "identifier": "69882",
            "j": 0.004162112174327815,
            "j_err": 5.228752664614091e-07,
            "mean_j": 0,
            "mean_j_err": 0,
            "mean_j_mswd": 0,
            "options": {},
            "position": 72,
            "position_jerr": null
        },
        {
            "analyses": [],
            "decay_constants": {},
            "identifier": "69883",
            "j": 0.004144267377599872,
            "j_err": 5.05603602514823e-07,
            "mean_j": 0,
            "mean_j_err": 0,
            "mean_j_mswd": 0,
            "options": {},
            "position": 73,
            "position_jerr": null
        },
        {
            "analyses": [],
            "decay_constants": {},
            "identifier": "69884",
            "j": 0.004126858875680034,
            "j_err": 4.878432607174424e-07,
            "mean_j": 0,
            "mean_j_err": 0,
            "mean_j_mswd": 0,
            "options": {},
            "position": 74,
            "position_jerr": null
        },
        {
            "analyses": [],
            "decay_constants": {},
            "identifier": "69885",
            "j": 0.0041103710376530316,
            "j_err": 4.701504407256085e-07,
            "mean_j": 0,
            "mean_j_err": 0,
            "mean_j_mswd": 0,
            "options": {},
            "position": 75,
            "position_jerr": null
        },
        {
            "analyses": [],
            "decay_constants": {},
            "identifier": "69886",
            "j": 0.004095272109497642,
            "j_err": 4.493153070090148e-07,
            "mean_j": 0,
            "mean_j_err": 0,
            "mean_j_mswd": 0,
            "options": {},
            "position": 76,
            "position_jerr": null
        },
        {
            "analyses": [],
            "decay_constants": {},
            "identifier": "69887",
            "j": 0.004082030337192646,
            "j_err": 4.2918732780673195e-07,
            "mean_j": 0,
            "mean_j_err": 0,
            "mean_j_mswd": 0,
            "options": {},
            "position": 77,
            "position_jerr": null
        },
        {
            "analyses": [],
            "decay_constants": {},
            "identifier": "69888",
            "j": 0.004071007815784015,
            "j_err": 4.1062793286152667e-07,
            "mean_j": 0,
            "mean_j_err": 0,
            "mean_j_mswd": 0,
            "options": {},
            "position": 78,
            "position_jerr": null
        },
        {
            "analyses": [],
            "decay_constants": {},
            "identifier": "69889",
            "j": 0.0040625145567205765,
            "j_err": 3.999281581783667e-07,
            "mean_j": 0,
            "mean_j_err": 0,
            "mean_j_mswd": 0,
            "options": {},
            "position": 79,
            "position_jerr": null
        },
        {
            "analyses": [],
            "decay_constants": {},
            "identifier": "69890",
            "j": 0.004056810471592543,
            "j_err": 3.8667007694978224e-07,
            "mean_j": 0,
            "mean_j_err": 0,
            "mean_j_mswd": 0,
            "options": {},
            "position": 80,
            "position_jerr": null
        },
        {
            "analyses": [],
            "decay_constants": {},
            "identifier": "69891",
            "j": 0.004070854724622164,
            "j_err": 3.3326881902899925e-07,
            "mean_j": 0,
            "mean_j_err": 0,
            "mean_j_mswd": 0,
            "options": {},
            "position": 81,
            "position_jerr": null
        },
        {
            "analyses": [],
            "decay_constants": {},
            "identifier": "69892",
            "j": 0.004071489137948077,
            "j_err": 3.3229428166419536e-07,
            "mean_j": 0,
            "mean_j_err": 0,
            "mean_j_mswd": 0,
            "options": {},
            "position": 82,
            "position_jerr": null
        },
        {
            "analyses": [],
            "decay_constants": {},
            "identifier": "69893",
            "j": 0.004075936501662041,
            "j_err": 3.3333275480661494e-07,
            "mean_j": 0,
            "mean_j_err": 0,
            "mean_j_mswd": 0,
            "options": {},
            "position": 83,
            "position_jerr": null
        },
        {
            "analyses": [],
            "decay_constants": {},
            "identifier": "69894",
            "j": 0.004084024188668935,
            "j_err": 3.43734677555227e-07,
            "mean_j": 0,
            "mean_j_err": 0,
            "mean_j_mswd": 0,
            "options": {},
            "position": 84,
            "position_jerr": null
        },
        {
            "analyses": [],
            "decay_constants": {},
            "identifier": "69895",
            "j": 0.004095413402389584,
            "j_err": 3.5262252452785377e-07,
            "mean_j": 0,
            "mean_j_err": 0,
            "mean_j_mswd": 0,
            "options": {},
            "position": 85,
            "position_jerr": null
        },
        {
            "analyses": [],
            "decay_constants": {},
            "identifier": "69896",
            "j": 0.004109583306852568,
            "j_err": 3.6738714158239393e-07,
            "mean_j": 0,
            "mean_j_err": 0,
            "mean_j_mswd": 0,
            "options": {},
            "position": 86,
            "position_jerr": null
        },
        {
            "analyses": [],
            "decay_constants": {},
            "identifier": "69897",
            "j": 0.004125923038259604,
            "j_err": 3.821513780419771e-07,
            "mean_j": 0,
            "mean_j_err": 0,
            "mean_j_mswd": 0,
            "options": {},
            "position": 87,
            "position_jerr": null
        },
        {
            "analyses": [],
            "decay_constants": {},
            "identifier": "69898",
            "j": 0.004143699711971402,
            "j_err": 3.945953307800699e-07,
            "mean_j": 0,
            "mean_j_err": 0,
            "mean_j_mswd": 0,
            "options": {},
            "position": 88,
            "position_jerr": null
        },
        {
            "analyses": [],
            "decay_constants": {},
            "identifier": "69899",
            "j": 0.004162140515380429,
            "j_err": 4.0487883737896283e-07,
            "mean_j": 0,
            "mean_j_err": 0,
            "mean_j_mswd": 0,
            "options": {},
            "position": 89,
            "position_jerr": null
        },
        {
            "analyses": [],
            "decay_constants": {},
            "identifier": "69900",
            "j": 0.004180460733448002,
            "j_err": 4.167904561122282e-07,
            "mean_j": 0,
            "mean_j_err": 0,
            "mean_j_mswd": 0,
            "options": {},
            "position": 90,
            "position_jerr": null
        },
        {
            "analyses": [],
            "decay_constants": {},
            "identifier": "69901",
            "j": 0.004197863748704293,
            "j_err": 4.2669779304053367e-07,
            "mean_j": 0,
            "mean_j_err": 0,
            "mean_j_mswd": 0,
            "options": {},
            "position": 91,
            "position_jerr": null
        },
        {
            "analyses": [],
            "decay_constants": {},
            "identifier": "69902",
            "j": 0.004213569066785416,
            "j_err": 4.379342850972975e-07,
            "mean_j": 0,
            "mean_j_err": 0,
            "mean_j_mswd": 0,
            "options": {},
            "position": 92,
            "position_jerr": null
        },
        {
            "analyses": [],
            "decay_constants": {},
            "identifier": "69903",
            "j": 0.00422689837678325,
            "j_err": 4.487159840276295e-07,
            "mean_j": 0,
            "mean_j_err": 0,
            "mean_j_mswd": 0,
            "options": {},
            "position": 93,
            "position_jerr": null
        },
        {
            "analyses": [],
            "decay_constants": {},
            "identifier": "69904",
            "j": 0.004237251493185383,
            "j_err": 4.5702416793897094e-07,
            "mean_j": 0,
            "mean_j_err": 0,
            "mean_j_mswd": 0,
            "options": {},
            "position": 94,
            "position_jerr": null
        },
        {
            "analyses": [],
            "decay_constants": {},
            "identifier": "69905",
            "j": 0.004244182497532308,
            "j_err": 4.6839507099560554e-07,
            "mean_j": 0,
            "mean_j_err": 0,
            "mean_j_mswd": 0,
            "options": {},
            "position": 95,
            "position_jerr": null
        },
        {
            "analyses": [],
            "decay_constants": {},
            "identifier": "69906",
            "j": 0.004247415608325614,
            "j_err": 4.804980067887981e-07,
            "mean_j": 0,
            "mean_j_err": 0,
            "mean_j_mswd": 0,
            "options": {},
            "position": 96,
            "position_jerr": null
        },
        {
            "analyses": [],
            "decay_constants": {},
            "identifier": "69907",
            "j": 0.004246781194999701,
            "j_err": 4.890615561902601e-07,
            "mean_j": 0,
            "mean_j_err": 0,
            "mean_j_mswd": 0,
            "options": {},
            "position": 97,
            "position_jerr": null
        },
        {
            "analyses": [],
            "decay_constants": {},
            "identifier": "69908",
            "j": 0.0042423338312857365,
            "j_err": 4.947899927680355e-07,
            "mean_j": 0,
            "mean_j_err": 0,
            "mean_j_mswd": 0,
            "options": {},
            "position": 98,
            "position_jerr": null
        },
        {
            "analyses": [],
            "decay_constants": {},
            "identifier": "69909",
            "j": 0.004234246144278843,
            "j_err": 4.964143028734223e-07,
            "mean_j": 0,
            "mean_j_err": 0,
            "mean_j_mswd": 0,
            "options": {},
            "position": 99,
            "position_jerr": null
        },
        {
            "analyses": [],
            "decay_constants": {},
            "identifier": "69910",
            "j": 0.0042228569305581935,
            "j_err": 4.982526037461192e-07,
            "mean_j": 0,
            "mean_j_err": 0,
            "mean_j_mswd": 0,
            "options": {},
            "position": 100,
            "position_jerr": null
        },
        {
            "analyses": [],
            "decay_constants": {},
            "identifier": "69911",
            "j": 0.00420868702609521,
            "j_err": 4.94809792532103e-07,
            "mean_j": 0,
            "mean_j_err": 0,
            "mean_j_mswd": 0,
            "options": {},
            "position": 101,
            "position_jerr": null
        },
        {
            "analyses": [],
            "decay_constants": {},
            "identifier": "69912",
            "j": 0.004192347294688174,
            "j_err": 4.873173147177579e-07,
            "mean_j": 0,
            "mean_j_err": 0,
            "mean_j_mswd": 0,
            "options": {},
            "position": 102,
            "position_jerr": null
        },
        {
            "analyses": [],
            "decay_constants": {},
            "identifier": "69913",
            "j": 0.004174570620976376,
            "j_err": 4.7557940355356894e-07,
            "mean_j": 0,
            "mean_j_err": 0,
            "mean_j_mswd": 0,
            "options": {},
            "position": 103,
            "position_jerr": null
        },
        {
            "analyses": [],
            "decay_constants": {},
            "identifier": "69914",
            "j": 0.004156129817567349,
            "j_err": 4.578749804904224e-07,
            "mean_j": 0,
            "mean_j_err": 0,
            "mean_j_mswd": 0,
            "options": {},
            "position": 104,
            "position_jerr": null
        },
        {
            "analyses": [],
            "decay_constants": {},
            "identifier": "69915",
            "j": 0.0041378095994997754,
            "j_err": 4.37934077319318e-07,
            "mean_j": 0,
            "mean_j_err": 0,
            "mean_j_mswd": 0,
            "options": {},
            "position": 105,
            "position_jerr": null
        },
        {
            "analyses": [],
            "decay_constants": {},
            "identifier": "69916",
            "j": 0.004120406584243485,
            "j_err": 4.175253861546968e-07,
            "mean_j": 0,
            "mean_j_err": 0,
            "mean_j_mswd": 0,
            "options": {},
            "position": 106,
            "position_jerr": null
        },
        {
            "analyses": [],
            "decay_constants": {},
            "identifier": "69917",
            "j": 0.004104701266162362,
            "j_err": 3.9783485064557053e-07,
            "mean_j": 0,
            "mean_j_err": 0,
            "mean_j_mswd": 0,
            "options": {},
            "position": 107,
            "position_jerr": null
        },
        {
            "analyses": [],
            "decay_constants": {},
            "identifier": "69918",
            "j": 0.004091371956164528,
            "j_err": 3.7406538428088046e-07,
            "mean_j": 0,
            "mean_j_err": 0,
            "mean_j_mswd": 0,
            "options": {},
            "position": 108,
            "position_jerr": null
        },
        {
            "analyses": [],
            "decay_constants": {},
            "identifier": "69919",
            "j": 0.004081018839762395,
            "j_err": 3.54358748943978e-07,
            "mean_j": 0,
            "mean_j_err": 0,
            "mean_j_mswd": 0,
            "options": {},
            "position": 109,
            "position_jerr": null
        },
        {
            "analyses": [],
            "decay_constants": {},
            "identifier": "69920",
            "j": 0.00407408783541547,
            "j_err": 3.399598381567977e-07,
            "mean_j": 0,
            "mean_j_err": 0,
            "mean_j_mswd": 0,
            "options": {},
            "position": 110,
            "position_jerr": null
        },
        {
            "analyses": [],
            "decay_constants": {},
            "identifier": "69921",
            "j": 0.004081191547593196,
            "j_err": 5.683398833736202e-07,
            "mean_j": 0,
            "mean_j_err": 0,
            "mean_j_mswd": 0,
            "options": {},
            "position": 111,
            "position_jerr": null
        },
        {
            "analyses": [],
            "decay_constants": {},
            "identifier": "69922",
            "j": 0.00408154033423683,
            "j_err": 5.639781065639393e-07,
            "mean_j": 0,
            "mean_j_err": 0,
            "mean_j_mswd": 0,
            "options": {},
            "position": 112,
            "position_jerr": null
        },
        {
            "analyses": [],
            "decay_constants": {},
            "identifier": "69923",
            "j": 0.004086650282634505,
            "j_err": 5.528360914573891e-07,
            "mean_j": 0,
            "mean_j_err": 0,
            "mean_j_mswd": 0,
            "options": {},
            "position": 113,
            "position_jerr": null
        },
        {
            "analyses": [],
            "decay_constants": {},
            "identifier": "69924",
            "j": 0.004096237342873234,
            "j_err": 5.343916369182492e-07,
            "mean_j": 0,
            "mean_j_err": 0,
            "mean_j_mswd": 0,
            "options": {},
            "position": 114,
            "position_jerr": null
        },
        {
            "analyses": [],
            "decay_constants": {},
            "identifier": "69925",
            "j": 0.004109580589863519,
            "j_err": 5.23324407542866e-07,
            "mean_j": 0,
            "mean_j_err": 0,
            "mean_j_mswd": 0,
            "options": {},
            "position": 115,
            "position_jerr": null
        },
        {
            "analyses": [],
            "decay_constants": {},
            "identifier": "69926",
            "j": 0.0041258051564358805,
            "j_err": 5.15894886302237e-07,
            "mean_j": 0,
            "mean_j_err": 0,
            "mean_j_mswd": 0,
            "options": {},
            "position": 116,
            "position_jerr": null
        },
        {
            "analyses": [],
            "decay_constants": {},
            "identifier": "69927",
            "j": 0.00414379570544543,
            "j_err": 5.243931828731002e-07,
            "mean_j": 0,
            "mean_j_err": 0,
            "mean_j_mswd": 0,
            "options": {},
            "position": 117,
            "position_jerr": null
        },
        {
            "analyses": [],
            "decay_constants": {},
            "identifier": "69928",
            "j": 0.004162328940084646,
            "j_err": 5.393697480405562e-07,
            "mean_j": 0,
            "mean_j_err": 0,
            "mean_j_mswd": 0,
            "options": {},
            "position": 118,
            "position_jerr": null
        },
        {
            "analyses": [],
            "decay_constants": {},
            "identifier": "69929",
            "j": 0.004180137899184998,
            "j_err": 5.59104849385404e-07,
            "mean_j": 0,
            "mean_j_err": 0,
            "mean_j_mswd": 0,
            "options": {},
            "position": 119,
            "position_jerr": null
        },
        {
            "analyses": [],
            "decay_constants": {},
            "identifier": "69930",
            "j": 0.004196013679113725,
            "j_err": 5.754514020872625e-07,
            "mean_j": 0,
            "mean_j_err": 0,
            "mean_j_mswd": 0,
            "options": {},
            "position": 120,
            "position_jerr": null
        },
        {
            "analyses": [],
            "decay_constants": {},
            "identifier": "69931",
            "j": 0.0042088942797256,
            "j_err": 5.875247486689287e-07,
            "mean_j": 0,
            "mean_j_err": 0,
            "mean_j_mswd": 0,
            "options": {},
            "position": 121,
            "position_jerr": null
        },
        {
            "analyses": [],
            "decay_constants": {},
            "identifier": "69932",
            "j": 0.004217840454126087,
            "j_err": 5.957585981090163e-07,
            "mean_j": 0,
            "mean_j_err": 0,
            "mean_j_mswd": 0,
            "options": {},
            "position": 122,
            "position_jerr": null
        },
        {
            "analyses": [],
            "decay_constants": {},
            "identifier": "69933",
            "j": 0.004222306166236154,
            "j_err": 5.922542716538769e-07,
            "mean_j": 0,
            "mean_j_err": 0,
            "mean_j_mswd": 0,
            "options": {},
            "position": 123,
            "position_jerr": null
        },
        {
            "analyses": [],
            "decay_constants": {},
            "identifier": "69934",
            "j": 0.00422195737959252,
            "j_err": 5.804294936633652e-07,
            "mean_j": 0,
            "mean_j_err": 0,
            "mean_j_mswd": 0,
            "options": {},
            "position": 124,
            "position_jerr": null
        },
        {
            "analyses": [],
            "decay_constants": {},
            "identifier": "69935",
            "j": 0.004216847431194845,
            "j_err": 5.55482989217996e-07,
            "mean_j": 0,
            "mean_j_err": 0,
            "mean_j_mswd": 0,
            "options": {},
            "position": 125,
            "position_jerr": null
        },
        {
            "analyses": [],
            "decay_constants": {},
            "identifier": "69936",
            "j": 0.004207260370956116,
            "j_err": 5.32907068510827e-07,
            "mean_j": 0,
            "mean_j_err": 0,
            "mean_j_mswd": 0,
            "options": {},
            "position": 126,
            "position_jerr": null
        },
        {
            "analyses": [],
            "decay_constants": {},
            "identifier": "69937",
            "j": 0.004193917123965831,
            "j_err": 5.10851984686932e-07,
            "mean_j": 0,
            "mean_j_err": 0,
            "mean_j_mswd": 0,
            "options": {},
            "position": 127,
            "position_jerr": null
        },
        {
            "analyses": [],
            "decay_constants": {},
            "identifier": "69938",
            "j": 0.004177692557393469,
            "j_err": 4.987144224895219e-07,
            "mean_j": 0,
            "mean_j_err": 0,
            "mean_j_mswd": 0,
            "options": {},
            "position": 128,
            "position_jerr": null
        },
        {
            "analyses": [],
            "decay_constants": {},
            "identifier": "69939",
            "j": 0.00415970200838392,
            "j_err": 4.972573164552989e-07,
            "mean_j": 0,
            "mean_j_err": 0,
            "mean_j_mswd": 0,
            "options": {},
            "position": 129,
            "position_jerr": null
        },
        {
            "analyses": [],
            "decay_constants": {},
            "identifier": "69940",
            "j": 0.0041411687737447035,
            "j_err": 5.061929432789455e-07,
            "mean_j": 0,
            "mean_j_err": 0,
            "mean_j_mswd": 0,
            "options": {},
            "position": 130,
            "position_jerr": null
        },
        {
            "analyses": [],
            "decay_constants": {},
            "identifier": "69941",
            "j": 0.004123359814644352,
            "j_err": 5.199162100363676e-07,
            "mean_j": 0,
            "mean_j_err": 0,
            "mean_j_mswd": 0,
            "options": {},
            "position": 131,
            "position_jerr": null
        },
        {
            "analyses": [],
            "decay_constants": {},
            "identifier": "69942",
            "j": 0.004107484034715625,
            "j_err": 5.348920332505754e-07,
            "mean_j": 0,
            "mean_j_err": 0,
            "mean_j_mswd": 0,
            "options": {},
            "position": 132,
            "position_jerr": null
        },
        {
            "analyses": [],
            "decay_constants": {},
            "identifier": "69943",
            "j": 0.00409460343410375,
            "j_err": 5.561571345362165e-07,
            "mean_j": 0,
            "mean_j_err": 0,
            "mean_j_mswd": 0,
            "options": {},
            "position": 133,
            "position_jerr": null
        },
        {
            "analyses": [],
            "decay_constants": {},
            "identifier": "69944",
            "j": 0.004085657259703263,
            "j_err": 5.684359136621537e-07,
            "mean_j": 0,
            "mean_j_err": 0,
            "mean_j_mswd": 0,
            "options": {},
            "position": 134,
            "position_jerr": null
        },
        {
            "analyses": [],
            "decay_constants": {},
            "identifier": "69945",
            "j": 0.004089238817123721,
            "j_err": 4.840606363854412e-07,
            "mean_j": 0,
            "mean_j_err": 0,
            "mean_j_mswd": 0,
            "options": {},
            "position": 135,
            "position_jerr": null
        },
        {
            "analyses": [],
            "decay_constants": {},
            "identifier": "69946",
            "j": 0.004091328513977919,
            "j_err": 5.067183432398669e-07,
            "mean_j": 0,
            "mean_j_err": 0,
            "mean_j_mswd": 0,
            "options": {},
            "position": 136,
            "position_jerr": null
        },
        {
            "analyses": [],
            "decay_constants": {},
            "identifier": "69947",
            "j": 0.004099882571084349,
            "j_err": 5.342344998669006e-07,
            "mean_j": 0,
            "mean_j_err": 0,
            "mean_j_mswd": 0,
            "options": {},
            "position": 137,
            "position_jerr": null
        },
        {
            "analyses": [],
            "decay_constants": {},
            "identifier": "69948",
            "j": 0.004113839845911608,
            "j_err": 5.478505460051545e-07,
            "mean_j": 0,
            "mean_j_err": 0,
            "mean_j_mswd": 0,
            "options": {},
            "position": 138,
            "position_jerr": null
        },
        {
            "analyses": [],
            "decay_constants": {},
            "identifier": "69949",
            "j": 0.004131502753030486,
            "j_err": 5.505729820788964e-07,
            "mean_j": 0,
            "mean_j_err": 0,
            "mean_j_mswd": 0,
            "options": {},
            "position": 139,
            "position_jerr": null
        },
        {
            "analyses": [],
            "decay_constants": {},
            "identifier": "69950",
            "j": 0.004150791451385336,
            "j_err": 5.663622002972163e-07,
            "mean_j": 0,
            "mean_j_err": 0,
            "mean_j_mswd": 0,
            "options": {},
            "position": 140,
            "position_jerr": null
        },
        {
            "analyses": [],
            "decay_constants": {},
            "identifier": "69951",
            "j": 0.004169316190737506,
            "j_err": 5.829168664683008e-07,
            "mean_j": 0,
            "mean_j_err": 0,
            "mean_j_mswd": 0,
            "options": {},
            "position": 141,
            "position_jerr": null
        },
        {
            "analyses": [],
            "decay_constants": {},
            "identifier": "69952",
            "j": 0.004184889401002185,
            "j_err": 6.308003617280528e-07,
            "mean_j": 0,
            "mean_j_err": 0,
            "mean_j_mswd": 0,
            "options": {},
            "position": 142,
            "position_jerr": null
        },
        {
            "analyses": [],
            "decay_constants": {},
            "identifier": "69953",
            "j": 0.004195624042250606,
            "j_err": 6.85477846459132e-07,
            "mean_j": 0,
            "mean_j_err": 0,
            "mean_j_mswd": 0,
            "options": {},
            "position": 143,
            "position_jerr": null
        },
        {
            "analyses": [],
            "decay_constants": {},
            "identifier": "69954",
            "j": 0.004200191506775516,
            "j_err": 7.421232360744109e-07,
            "mean_j": 0,
            "mean_j_err": 0,
            "mean_j_mswd": 0,
            "options": {},
            "position": 144,
            "position_jerr": null
        },
        {
            "analyses": [],
            "decay_constants": {},
            "identifier": "69955",
            "j": 0.0041981018099213185,
            "j_err": 7.867047173990064e-07,
            "mean_j": 0,
            "mean_j_err": 0,
            "mean_j_mswd": 0,
            "options": {},
            "position": 145,
            "position_jerr": null
        },
        {
            "analyses": [],
            "decay_constants": {},
            "identifier": "69956",
            "j": 0.004189547752814889,
            "j_err": 7.974975188125211e-07,
            "mean_j": 0,
            "mean_j_err": 0,
            "mean_j_mswd": 0,
            "options": {},
            "position": 146,
            "position_jerr": null
        },
        {
            "analyses": [],
            "decay_constants": {},
            "identifier": "69957",
            "j": 0.004175590477987629,
            "j_err": 7.724105205292461e-07,
            "mean_j": 0,
            "mean_j_err": 0,
            "mean_j_mswd": 0,
            "options": {},
            "position": 147,
            "position_jerr": null
        },
        {
            "analyses": [],
            "decay_constants": {},
            "identifier": "69958",
            "j": 0.004157927570868752,
            "j_err": 7.138285117753236e-07,
            "mean_j": 0,
            "mean_j_err": 0,
            "mean_j_mswd": 0,
            "options": {},
            "position": 148,
            "position_jerr": null
        },
        {
            "analyses": [],
            "decay_constants": {},
            "identifier": "69959",
            "j": 0.0041386388725139014,
            "j_err": 6.403576786384194e-07,
            "mean_j": 0,
            "mean_j_err": 0,
            "mean_j_mswd": 0,
            "options": {},
            "position": 149,
            "position_jerr": null
        },
        {
            "analyses": [],
            "decay_constants": {},
            "identifier": "69960",
            "j": 0.004120114133161732,
            "j_err": 5.672534414723039e-07,
            "mean_j": 0,
            "mean_j_err": 0,
            "mean_j_mswd": 0,
            "options": {},
            "position": 150,
            "position_jerr": null
        },
        {
            "analyses": [],
            "decay_constants": {},
            "identifier": "69961",
            "j": 0.0041045409228970525,
            "j_err": 5.025581565035123e-07,
            "mean_j": 0,
            "mean_j_err": 0,
            "mean_j_mswd": 0,
            "options": {},
            "position": 151,
            "position_jerr": null
        },
        {
            "analyses": [],
            "decay_constants": {},
            "identifier": "69962",
            "j": 0.004093806281648632,
            "j_err": 4.804908876774942e-07,
            "mean_j": 0,
            "mean_j_err": 0,
            "mean_j_mswd": 0,
            "options": {},
            "position": 152,
            "position_jerr": null
        }
    ],
    "z": 0.0
}